nidhoggr/core/__init__.py
nidhoggr/core/config.py
nidhoggr/core/crypto.py
nidhoggr/core/repository.py
nidhoggr/core/response.py
nidhoggr/core/texture.py
nidhoggr/core/user.py
nidhoggr/requests/__init__.py
nidhoggr/requests/core.py
nidhoggr/requests/textures.py
nidhoggr/requests/users.py
nidhoggr_core-0.11.1.dist-info/LICENSE
nidhoggr_core-0.11.1.dist-info/METADATA
nidhoggr_core-0.11.1.dist-info/WHEEL
nidhoggr_core-0.11.1.dist-info/top_level.txt
nidhoggr_core-0.11.1.dist-info/RECORD
